odoo/addons/l10n_br_account_nfe/README.rst
odoo/addons/l10n_br_account_nfe/__init__.py
odoo/addons/l10n_br_account_nfe/__manifest__.py
odoo/addons/l10n_br_account_nfe/hooks.py
odoo/addons/l10n_br_account_nfe/demo/account_invoice_sn_demo.xml
odoo/addons/l10n_br_account_nfe/i18n/l10n_br_account_nfe.pot
odoo/addons/l10n_br_account_nfe/i18n/pt_BR.po
odoo/addons/l10n_br_account_nfe/models/__init__.py
odoo/addons/l10n_br_account_nfe/models/account_payment_mode.py
odoo/addons/l10n_br_account_nfe/models/document.py
odoo/addons/l10n_br_account_nfe/models/leiauteNFe.py
odoo/addons/l10n_br_account_nfe/readme/CONFIGURE.rst
odoo/addons/l10n_br_account_nfe/readme/CONTRIBUTORS.rst
odoo/addons/l10n_br_account_nfe/readme/DESCRIPTION.rst
odoo/addons/l10n_br_account_nfe/readme/HISTORY.rst
odoo/addons/l10n_br_account_nfe/readme/ROADMAP.rst
odoo/addons/l10n_br_account_nfe/readme/USAGE.rst
odoo/addons/l10n_br_account_nfe/report/__init__.py
odoo/addons/l10n_br_account_nfe/report/danfe_report.xml
odoo/addons/l10n_br_account_nfe/report/ir_actions_report.py
odoo/addons/l10n_br_account_nfe/static/description/icon.png
odoo/addons/l10n_br_account_nfe/static/description/index.html
odoo/addons/l10n_br_account_nfe/tests/__init__.py
odoo/addons/l10n_br_account_nfe/tests/test_nfce_contingency.py
odoo/addons/l10n_br_account_nfe/tests/test_nfe_danfe_account.py
odoo/addons/l10n_br_account_nfe/tests/test_nfe_generate_tags_cobr_dup_pag.py
odoo/addons/l10n_br_account_nfe/tests/test_nfe_with_ipi.py
odoo/addons/l10n_br_account_nfe/views/account_payment_mode.xml
odoo14_addon_l10n_br_account_nfe-14.0.6.1.1.dist-info/METADATA
odoo14_addon_l10n_br_account_nfe-14.0.6.1.1.dist-info/WHEEL
odoo14_addon_l10n_br_account_nfe-14.0.6.1.1.dist-info/top_level.txt
odoo14_addon_l10n_br_account_nfe-14.0.6.1.1.dist-info/RECORD
